timezone_field/__init__.py
timezone_field/fields.py
timezone_field/forms.py
timezone_field/models.py
timezone_field/utils.py
ambition_django_timezone_field-2.0.4.dist-info/LICENSE.txt
ambition_django_timezone_field-2.0.4.dist-info/METADATA
ambition_django_timezone_field-2.0.4.dist-info/WHEEL
ambition_django_timezone_field-2.0.4.dist-info/top_level.txt
ambition_django_timezone_field-2.0.4.dist-info/RECORD
