Metadata-Version: 2.1
Name: ambition-django-timezone-field
Version: 2.0.4
Summary: A Django app providing database and form fields for pytz timezone objects.
Home-page: http://github.com/mfogel/django-timezone-field/
Author: Mike Fogel
Author-email: mike@fogel.ca
License: BSD
Platform: UNKNOWN
Classifier: Development Status :: 4 - Beta
Classifier: Environment :: Web Environment
Classifier: Intended Audience :: Developers
Classifier: License :: OSI Approved :: BSD License
Classifier: Operating System :: OS Independent
Classifier: Programming Language :: Python
Classifier: Programming Language :: Python :: 3
Classifier: Programming Language :: Python :: 3.6
Classifier: Programming Language :: Python :: 3.7
Classifier: Programming Language :: Python :: 3.8
Classifier: Topic :: Utilities
Classifier: Framework :: Django
Requires-Dist: Django (>=2.2)
Requires-Dist: pytz
Requires-Dist: six
